purePyAES/__init__.py
purePyAES/py_aes.py
purepyaes-0.0.5.dist-info/METADATA
purepyaes-0.0.5.dist-info/WHEEL
purepyaes-0.0.5.dist-info/licenses/LICENSE.txt
purepyaes-0.0.5.dist-info/RECORD
