Metadata-Version: 2.4
Name: purePyAES
Version: 0.0.5
Summary: AES encryption library written entirely in pure python. No other system dependencies required.
Project-URL: Homepage, https://github.com/darkerego/purePythonAes.git
Project-URL: Issues, https://github.com/darkerego/purePythonAes/issues
License-Expression: MIT
License-File: LICENSE.txt
Classifier: Operating System :: OS Independent
Classifier: Programming Language :: Python :: 3
Requires-Python: >=3.11.2
